{"name": "D. Xenolith? Hippodrome?", "group": "Codeforces - April Fools Day Contest 2021", "url": "https://codeforces.com/contest/1505/problem/D", "interactive": false, "memoryLimit": 256, "timeLimit": 1000, "tests": [{"input": "2 3\n", "output": "YES\n"}, {"input": "3 2\n", "output": "NO\n"}, {"input": "33 16\n", "output": "YES\n"}, {"input": "26 5\n", "output": "NO\n"}], "testType": "single", "input": {"type": "stdin"}, "output": {"type": "stdout"}, "languages": {"java": {"mainClass": "Main", "taskClass": "DXenolithHippodrome"}}, "batch": {"id": "0ab78805-d939-4587-9217-372a54a0763c", "size": 9}}